odoo8_addon_l10n_lu_mis_reports-8.0.1.1.0-py2.7-nspkg.pth
odoo8_addon_l10n_lu_mis_reports-8.0.1.1.0.dist-info/DESCRIPTION.rst
odoo8_addon_l10n_lu_mis_reports-8.0.1.1.0.dist-info/METADATA
odoo8_addon_l10n_lu_mis_reports-8.0.1.1.0.dist-info/RECORD
odoo8_addon_l10n_lu_mis_reports-8.0.1.1.0.dist-info/WHEEL
odoo8_addon_l10n_lu_mis_reports-8.0.1.1.0.dist-info/metadata.json
odoo8_addon_l10n_lu_mis_reports-8.0.1.1.0.dist-info/namespace_packages.txt
odoo8_addon_l10n_lu_mis_reports-8.0.1.1.0.dist-info/top_level.txt
odoo_addons/l10n_lu_mis_reports/README.rst
odoo_addons/l10n_lu_mis_reports/__init__.py
odoo_addons/l10n_lu_mis_reports/__openerp__.py
odoo_addons/l10n_lu_mis_reports/data/mis_report_abr_bs.xml
odoo_addons/l10n_lu_mis_reports/data/mis_report_abr_pl.xml
odoo_addons/l10n_lu_mis_reports/data/mis_report_bs.xml
odoo_addons/l10n_lu_mis_reports/data/mis_report_bs_2016.xml
odoo_addons/l10n_lu_mis_reports/data/mis_report_ca.xml
odoo_addons/l10n_lu_mis_reports/data/mis_report_pl.xml
odoo_addons/l10n_lu_mis_reports/data/mis_report_pl_2016.xml
